valphor/__init__.py
valphor/__init__.pyi
valphor/hash.py
valphor/py.typed
valphor/salt.py
valphor/verify.py
valphor-1.1.0.dist-info/licenses/LICENSE
valphor-1.1.0.dist-info/METADATA
valphor-1.1.0.dist-info/WHEEL
valphor-1.1.0.dist-info/top_level.txt
valphor-1.1.0.dist-info/RECORD
