Metadata-Version: 2.4
Name: valphor
Version: 1.1.0
Summary: A hashing algorithm that is slower and more secure than bcrypt.
Home-page: https://github.com/IMJNMHTODRLA/valphor/
Author: RedGold
Author-email: sola001.w@gmail.com
License: MIT
Project-URL: Source Repository, https://github.com/IMJNMHTODRLA/valphor/
Requires-Python: >=3.6
License-File: LICENSE
Dynamic: license-file
